{
    "businessEntity": {
        "businessName": "Tech Innovations Inc.",
        "dba": "TechInno",
        "address": "500 Tech Park, Silicon Valley, CA, 94025",
        "contactInfo": {
            "phone": "800-123-4567",
            "email": "contact@techinno.com"
        },
        "entityType": "Corporation",
        "ein": "98-7654321",
        "incorporationDetails": {
            "state": "California",
            "date": "2010-04-12"
        },
        "owners": [
            {
                "name": "John Doe",
                "title": "CEO",
                "ownershipPercentage": 40
            },
            {
                "name": "Jane Smith",
                "title": "CFO",
                "ownershipPercentage": 30
            }
        ]
    },
    "accountDetails": {
        "accountNumber": "9876543210",
        "accountType": "Business Checking",
        "openingDate": "2011-05-20",
        "currentBalance": 500000.00
    },
    "transactionHistory": [
        {
            "date": "2023-12-01",
            "amount": 20000.00,
            "type": "Wire Transfer",
            "description": "Payment to Vendor X",
            "transactionId": "TX987654321001"
        },
        {
            "date": "2023-12-03",
            "amount": -15000.00,
            "type": "ATM Withdrawal",
            "description": "Withdrawal for Operational Expenses",
            "transactionId": "TX987654321002"
        }
    ],
    "associatedAccounts": [
        {
            "accountNumber": "1234567890",
            "accountType": "Business Savings",
            "bankName": "Silicon Valley Bank",
            "balance": 1000000.00
        }
    ],
    "signatoryInformation": [
        {
            "name": "John Doe",
            "title": "CEO",
            "dob": "1975-06-15",
            "address": "123 Main St, Silicon Valley, CA, 94025"
        },
        {
            "name": "Jane Smith",
            "title": "CFO",
            "dob": "1980-09-10",
            "address": "456 Elm St, Silicon Valley, CA, 94025"
        }
    ],
    "loanInformation": [
        {
            "loanNumber": "LN123456789",
            "type": "Business Loan",
            "amount": 250000.00,
            "dateIssued": "2020-08-01",
            "dueDate": "2025-08-01",
            "interestRate": 5.0,
            "status": "Active"
        }
    ],
    "auditTrails": [
        {
            "action": "Account Access",
            "date": "2023-11-30",
            "performedBy": "CFO Jane Smith",
            "description": "Accessed account for monthly review"
        }
    ],
    "communicationRecords": {
        "emails": [
            {
                "date": "2023-11-25",
                "subject": "Inquiry about Wire Transfer Fees",
                "status": "Replied"
            }
        ],
        "calls": [
            {
                "date": "2023-11-20",
                "time": "14:30",
                "duration": "00:10:22",
                "nature": "Discussion about loan repayment options"
            }
        ]
    },
    "suspiciousActivities": [
        {
            "date": "2023-12-03",
            "activity": "Unusually large ATM withdrawal",
            "amount": 15000.00,
            "investigationStatus": "Ongoing"
        }
    ]
}
